{
  "required": true,
  "minVersion": "0.8",
  "package": "calebxzhou.rdi.mixin",
  "compatibilityLevel": "JAVA_21",
  "client": [
    "AMinecraft",
    "mChat",
    "mCrash",
    "mFastCreateMojangService",
    "mFastCreateMojangService2",
    "mHttpTexture",
    "mJpgImage",
    "mPlayerTabOverlay",
    "mRAuth",
    "mScreenTransition",
    "mSkin",
    "mTitleScreen"
  ],
  "injectors": {
    "defaultRequire": 1
  },
  "mixins": [
    "mAllowChineseArgument",
    "mAllowChineseName",
    "mAlwaysOfflineMode",
    "mPlayerInfoUpdate",
    "mProxyConnect",
    "mServerboundHelloPacket",
    "mServiceKeyInfo",
    "mTextureUrlChecker",
    "gameplay.mPlayer",
    "mui.mNoBlur"
  ]
}